{
  "sold": {
    "50": {
      "name": "bouzzy",
      "linkUrl": "https://toto.com/",
      "ts": 1756135868773,
      "regionId": "r_mer9ycmd_dk19"
    },
    "51": {
      "name": "bouzzy",
      "linkUrl": "https://toto.com/",
      "ts": 1756135868773,
      "regionId": "r_mer9ycmd_dk19"
    },
    "52": {
      "name": "bouzzy",
      "linkUrl": "https://toto.com/",
      "ts": 1756135868773,
      "regionId": "r_mer9ycmd_dk19"
    },
    "53": {
      "name": "bouzzy",
      "linkUrl": "https://toto.com/",
      "ts": 1756135868773,
      "regionId": "r_mer9ycmd_dk19"
    },
    "150": {
      "name": "bouzzy",
      "linkUrl": "https://toto.com/",
      "ts": 1756135868773,
      "regionId": "r_mer9ycmd_dk19"
    },
    "151": {
      "name": "bouzzy",
      "linkUrl": "https://toto.com/",
      "ts": 1756135868773,
      "regionId": "r_mer9ycmd_dk19"
    },
    "152": {
      "name": "bouzzy",
      "linkUrl": "https://toto.com/",
      "ts": 1756135868773,
      "regionId": "r_mer9ycmd_dk19"
    },
    "153": {
      "name": "bouzzy",
      "linkUrl": "https://toto.com/",
      "ts": 1756135868773,
      "regionId": "r_mer9ycmd_dk19"
    },
    "250": {
      "name": "bouzzy",
      "linkUrl": "https://toto.com/",
      "ts": 1756135868773,
      "regionId": "r_mer9ycmd_dk19"
    },
    "251": {
      "name": "bouzzy",
      "linkUrl": "https://toto.com/",
      "ts": 1756135868773,
      "regionId": "r_mer9ycmd_dk19"
    },
    "252": {
      "name": "bouzzy",
      "linkUrl": "https://toto.com/",
      "ts": 1756135868773,
      "regionId": "r_mer9ycmd_dk19"
    },
    "253": {
      "name": "bouzzy",
      "linkUrl": "https://toto.com/",
      "ts": 1756135868773,
      "regionId": "r_mer9ycmd_dk19"
    }
  },
  "locks": {
    "70": {
      "uid": "65a12b40-681e-48f5-8b1b-5cd948dc3b69",
      "until": 1756136082262
    },
    "71": {
      "uid": "65a12b40-681e-48f5-8b1b-5cd948dc3b69",
      "until": 1756136082262
    },
    "72": {
      "uid": "65a12b40-681e-48f5-8b1b-5cd948dc3b69",
      "until": 1756136082262
    },
    "73": {
      "uid": "65a12b40-681e-48f5-8b1b-5cd948dc3b69",
      "until": 1756136082262
    },
    "74": {
      "uid": "65a12b40-681e-48f5-8b1b-5cd948dc3b69",
      "until": 1756136082262
    },
    "170": {
      "uid": "65a12b40-681e-48f5-8b1b-5cd948dc3b69",
      "until": 1756136082262
    },
    "171": {
      "uid": "65a12b40-681e-48f5-8b1b-5cd948dc3b69",
      "until": 1756136082262
    },
    "172": {
      "uid": "65a12b40-681e-48f5-8b1b-5cd948dc3b69",
      "until": 1756136082262
    },
    "173": {
      "uid": "65a12b40-681e-48f5-8b1b-5cd948dc3b69",
      "until": 1756136082262
    },
    "174": {
      "uid": "65a12b40-681e-48f5-8b1b-5cd948dc3b69",
      "until": 1756136082262
    },
    "270": {
      "uid": "65a12b40-681e-48f5-8b1b-5cd948dc3b69",
      "until": 1756136082262
    },
    "271": {
      "uid": "65a12b40-681e-48f5-8b1b-5cd948dc3b69",
      "until": 1756136082262
    },
    "272": {
      "uid": "65a12b40-681e-48f5-8b1b-5cd948dc3b69",
      "until": 1756136082262
    },
    "273": {
      "uid": "65a12b40-681e-48f5-8b1b-5cd948dc3b69",
      "until": 1756136082262
    },
    "274": {
      "uid": "65a12b40-681e-48f5-8b1b-5cd948dc3b69",
      "until": 1756136082262
    },
    "359": {
      "uid": "c27f40ce-b5a2-450d-aec6-edea7dcd45f1",
      "until": 1756136078265
    },
    "360": {
      "uid": "c27f40ce-b5a2-450d-aec6-edea7dcd45f1",
      "until": 1756136078265
    },
    "361": {
      "uid": "c27f40ce-b5a2-450d-aec6-edea7dcd45f1",
      "until": 1756136078265
    },
    "362": {
      "uid": "c27f40ce-b5a2-450d-aec6-edea7dcd45f1",
      "until": 1756136078265
    },
    "363": {
      "uid": "c27f40ce-b5a2-450d-aec6-edea7dcd45f1",
      "until": 1756136078265
    },
    "364": {
      "uid": "c27f40ce-b5a2-450d-aec6-edea7dcd45f1",
      "until": 1756136078265
    },
    "370": {
      "uid": "65a12b40-681e-48f5-8b1b-5cd948dc3b69",
      "until": 1756136082262
    },
    "371": {
      "uid": "65a12b40-681e-48f5-8b1b-5cd948dc3b69",
      "until": 1756136082262
    },
    "372": {
      "uid": "65a12b40-681e-48f5-8b1b-5cd948dc3b69",
      "until": 1756136082262
    },
    "373": {
      "uid": "65a12b40-681e-48f5-8b1b-5cd948dc3b69",
      "until": 1756136082262
    },
    "374": {
      "uid": "65a12b40-681e-48f5-8b1b-5cd948dc3b69",
      "until": 1756136082262
    },
    "459": {
      "uid": "c27f40ce-b5a2-450d-aec6-edea7dcd45f1",
      "until": 1756136078265
    },
    "460": {
      "uid": "c27f40ce-b5a2-450d-aec6-edea7dcd45f1",
      "until": 1756136078265
    },
    "461": {
      "uid": "c27f40ce-b5a2-450d-aec6-edea7dcd45f1",
      "until": 1756136078265
    },
    "462": {
      "uid": "c27f40ce-b5a2-450d-aec6-edea7dcd45f1",
      "until": 1756136078265
    },
    "463": {
      "uid": "c27f40ce-b5a2-450d-aec6-edea7dcd45f1",
      "until": 1756136078265
    },
    "464": {
      "uid": "c27f40ce-b5a2-450d-aec6-edea7dcd45f1",
      "until": 1756136078265
    },
    "559": {
      "uid": "c27f40ce-b5a2-450d-aec6-edea7dcd45f1",
      "until": 1756136078265
    },
    "560": {
      "uid": "c27f40ce-b5a2-450d-aec6-edea7dcd45f1",
      "until": 1756136078265
    },
    "561": {
      "uid": "c27f40ce-b5a2-450d-aec6-edea7dcd45f1",
      "until": 1756136078265
    },
    "562": {
      "uid": "c27f40ce-b5a2-450d-aec6-edea7dcd45f1",
      "until": 1756136078265
    },
    "563": {
      "uid": "c27f40ce-b5a2-450d-aec6-edea7dcd45f1",
      "until": 1756136078265
    },
    "564": {
      "uid": "c27f40ce-b5a2-450d-aec6-edea7dcd45f1",
      "until": 1756136078265
    },
    "659": {
      "uid": "c27f40ce-b5a2-450d-aec6-edea7dcd45f1",
      "until": 1756136078265
    },
    "660": {
      "uid": "c27f40ce-b5a2-450d-aec6-edea7dcd45f1",
      "until": 1756136078265
    },
    "661": {
      "uid": "c27f40ce-b5a2-450d-aec6-edea7dcd45f1",
      "until": 1756136078265
    },
    "662": {
      "uid": "c27f40ce-b5a2-450d-aec6-edea7dcd45f1",
      "until": 1756136078265
    },
    "663": {
      "uid": "c27f40ce-b5a2-450d-aec6-edea7dcd45f1",
      "until": 1756136078265
    },
    "664": {
      "uid": "c27f40ce-b5a2-450d-aec6-edea7dcd45f1",
      "until": 1756136078265
    },
    "759": {
      "uid": "c27f40ce-b5a2-450d-aec6-edea7dcd45f1",
      "until": 1756136078265
    },
    "760": {
      "uid": "c27f40ce-b5a2-450d-aec6-edea7dcd45f1",
      "until": 1756136078265
    },
    "761": {
      "uid": "c27f40ce-b5a2-450d-aec6-edea7dcd45f1",
      "until": 1756136078265
    },
    "762": {
      "uid": "c27f40ce-b5a2-450d-aec6-edea7dcd45f1",
      "until": 1756136078265
    },
    "763": {
      "uid": "c27f40ce-b5a2-450d-aec6-edea7dcd45f1",
      "until": 1756136078265
    },
    "764": {
      "uid": "c27f40ce-b5a2-450d-aec6-edea7dcd45f1",
      "until": 1756136078265
    },
    "859": {
      "uid": "c27f40ce-b5a2-450d-aec6-edea7dcd45f1",
      "until": 1756136078265
    },
    "860": {
      "uid": "c27f40ce-b5a2-450d-aec6-edea7dcd45f1",
      "until": 1756136078265
    },
    "861": {
      "uid": "c27f40ce-b5a2-450d-aec6-edea7dcd45f1",
      "until": 1756136078265
    },
    "862": {
      "uid": "c27f40ce-b5a2-450d-aec6-edea7dcd45f1",
      "until": 1756136078265
    },
    "863": {
      "uid": "c27f40ce-b5a2-450d-aec6-edea7dcd45f1",
      "until": 1756136078265
    },
    "864": {
      "uid": "c27f40ce-b5a2-450d-aec6-edea7dcd45f1",
      "until": 1756136078265
    }
  },
  "regions": {
    "r_mer9ycmd_dk19": {
      "imageUrl": "https://raw.githubusercontent.com/GRBUZ/infwallau/main/assets/images/r_mer9ycmd_dk19/test2_1756135870351_sn7zp7.jpg",
      "rect": {
        "x": 50,
        "y": 0,
        "w": 4,
        "h": 3
      }
    }
  }
}