{
  "status": "pending",
  "uid": "0cee897c-6ded-4fbb-b772-271b11ab045a",
  "name": "bouzzy",
  "linkUrl": "https://toto.com/",
  "blocks": [
    41,
    42,
    43,
    141,
    142,
    143,
    241,
    242,
    243,
    341,
    342,
    343,
    441,
    442,
    443,
    541,
    542,
    543
  ],
  "rect": {
    "x": 41,
    "y": 0,
    "w": 3,
    "h": 6
  },
  "regionId": "r_meytj8hh_1rpk",
  "image": {
    "repoPath": "staging/ord_meytj8hh_c06r/Capture-d__cran-2025-02-01-213031_1756592018786_rreh5f.png",
    "url": "https://raw.githubusercontent.com/GRBUZ/infwallau/main/staging/ord_meytj8hh_c06r/Capture-d__cran-2025-02-01-213031_1756592018786_rreh5f.png",
    "contentType": "image/png"
  },
  "amount": null,
  "currency": "USD",
  "createdAt": 1756592019904,
  "expiresAt": 1756593219904
}
